[
    {
        "SelectionText": "What is an augmentation",
        "TutorialSteps": [
            {
            "Id": null,
            "Message": "Augmentations in MirageXR are primitives that comprise the holographic part of the training experience of the user. A trainer can use different types of augmentations to construct the holographic experience, while the trainee perceives them as part of the learning experience.",
            "Position": 1,
            "BtnText": "Got it"
            }
        ],
        "EditModeOnly": false
    },
    {
        "SelectionText": "How to find augmentations",
        "TutorialSteps": [
            {
            "Id": null,
            "Message": "Look down to your feet and you will see an aura surrounding you, with connecting lines leading to where the action happens.",
            "Position": 1,
            "BtnText": "Got it"
            }
        ],
        "EditModeOnly": false
    },
    {
        "SelectionText": "How to add step title and description",
        "TutorialSteps": [
            {
            "Id": "step_info",
            "Message": "You can add or change the title and description of any step, just switch to the info tab.",
            "Position": 2,
            "BtnText": "Cancel"
            }
        ],
        "EditModeOnly": true
    },
    {
        "SelectionText": "How to add augmentations to a step",
        "TutorialSteps": [
            {
            "Id": "step_add_augmentation",
            "Message": "You can add augmentations by pressing the plus button here.",
            "Position": 0,
            "BtnText": "Cancel"
            }
        ],
        "EditModeOnly": true
    },
    {
        "SelectionText": "How to make changes to existing augmentations",
        "TutorialSteps": [
            {
            "Id": null,
            "Message": "Additional options for added augmentations can be accessed by pressing the three dots on the right side of an augmentation tile.",
            "Position": 2,
            "BtnText": "Got it"
            }
        ],
        "EditModeOnly": true
    },
    {
        "SelectionText": "Is there a way for an augmentation to stay for more than one step",
        "TutorialSteps": [
            {
            "Id": null,
            "Message": "You can make the same augmentation to be present in multiple steps. Tap on the settings of the augmentation (three dots on the right), choose keep-alive, and select the range of steps.",
            "Position": 1,
            "BtnText": "Got it"
            }
        ],
        "EditModeOnly": true
    }
]
